{
  "701" : {
    "time" : "武则天长安元年",
    "events" : ""
  },
  "702" : {
    "time" : "武则天长安二年",
    "events" : ""
  },
  "703" : {
    "time" : "武则天长安三年",
    "events" : ""
  },
  "704" : {
    "time" : "武则天长安四年",
    "events" : ""
  },
  "705" : {
    "time" : "唐中宗神龙元年",
    "events" : "李白开始发奋读书"
  },
  "706" : {
    "time" : "唐中宗神龙二年",
    "events" : ""
  },
  "707" : {
    "time" : "唐中宗神龙三年",
    "events" : ""
  },
  "708" : {
    "time" : "唐中宗神龙四年",
    "events" : ""
  },
  "709" : {
    "time" : "唐中宗神龙五年",
    "events" : ""
  },
  "710" : {
    "time" : "唐睿宗景云元年",
    "events" : "李白攻读《诗》、《书》及诸子百家"
  },
  "711" : {
    "time" : "唐睿宗景云二年",
    "events" : ""
  },
  "712" : {
    "time" : "唐玄宗先天元年",
    "events" : "李白十二岁, 该年杜甫出生"
  },
  "713" : {
    "time" : "唐玄宗开元元年",
    "events" : ""
  },
  "714" : {
    "time" : "唐玄宗开元二年",
    "events" : "李白开始吟诗作赋"
  },
  "715" : {
    "time" : "唐玄宗开元三年",
    "events" : "李白正值少年,已有诗赋多首,并得到一些社会名流的推崇"
  },
  "716" : {
    "time" : "唐玄宗开元四年",
    "events" : ""
  },
  "717" : {
    "time" : "唐玄宗开元五年",
    "events" : ""
  },
  "718" : {
    "time" : "唐玄宗开元六年",
    "events" : "李白先后出游剑阁、梓州（今三台县），增长了不少阅历与见识。"
  },
  "719" : {
    "time" : "唐玄宗开元七年",
    "events" : "李白从梓州(今绵阳三台县)返回大匡山(今江油市境内)继续隐居"
  },
  "720" : {
    "time" : "唐玄宗开元八年",
    "events" : "李白沿水路,乘船出游成都、峨眉山、渝州(今重庆)"
  },
  "721" : {
    "time" : "唐玄宗开元九年",
    "events" : "李白于春季从渝州(今重庆)归家, 该年冬季到达昌明(今江油)"
  },
  "722" : {
    "time" : "唐玄宗开元十年",
    "events" : "李白受邀前往江油都尉厅(今达州南坝镇)吟诗作赋, 此后隐居于匡山"
  },
  "723" : {
    "time" : "唐玄宗开元十一年",
    "events" : ""
  },
  "724" : {
    "time" : "唐玄宗开元十二年",
    "events" : "李白再游峨眉山, 然后舟行东下渝州(今重庆)"
  },
  "725" : {
    "time" : "唐玄宗开元十三年",
    "events" : "李白春季从渝州(今重庆)自三峡东下, 沿长江, 先后途经荆门(今宜都), 荆州(今江陵), 夏游洞庭湖, 庐山, 秋至金陵(今南京)"
  },
  "726" : {
    "time" : "唐玄宗开元十四年",
    "events" : "李白春季离开金陵(今南京), 前往江南, 先后游历广陵(今扬州), 姑苏, 越中(今绍兴), 嵊州, 秋季卧病于广陵(今扬州), 冬日北游汝州(今汝阳), 途径陈州(今淮阳), 受李邕推荐,后于襄阳结识孟浩然, 随之一同前往安陆"
  },
  "727" : {
    "time" : "唐玄宗开元十五年",
    "events" : "李白与宰相许圉师之孙女结婚, 结识元丹丘, 成家于安陆"
  },
  "728" : {
    "time" : "唐玄宗开元十六年",
    "events" : "李白随孟浩然出游江夏(今武汉)"
  },
  "729" : {
    "time" : "唐玄宗开元十七年",
    "events" : ""
  },
  "730" : {
    "time" : "唐玄宗开元十八年",
    "events" : "李白春日前往江夏(今武汉)送别孟浩然, 后前往长安都城, 寓居终南山, 秋游邢州(今岐山县和太白县), 冬游坊州(今黄陵县)"
  },
  "731" : {
    "time" : "唐玄宗开元十九年",
    "events" : "李白初夏离开长安, 沿渭河、黄河途径开封，到宋城(今商丘), 秋至嵩山, 后滞留洛阳"
  },
  "732" : {
    "time" : "唐玄宗开元二十年",
    "events" : "李白在洛阳结识元演、崔成甫, 秋季途径南阳, 返家安陆, 冬日与元演出游随州(今随县), 岁末，归家安陆"
  },
  "733" : {
    "time" : "唐玄宗开元二十一年",
    "events" : ""
  },
  "734" : {
    "time" : "唐玄宗开元二十二年",
    "events" : "李白出游襄阳, 荆州(今江陵), 暮春至江夏(今武汉), 滞留至秋归家安陆"
  },
  "735" : {
    "time" : "唐玄宗开元二十三年",
    "events" : "李白应友人元演之邀前往游历太原, 后滞留太原"
  },
  "736" : {
    "time" : "唐玄宗开元二十四年",
    "events" : "李白春季结识郭子仪, 一同出游雁门关, 后南下嵩山寻元丹丘, 襄阳寻孟浩然, 返家安陆"
  },
  "737" : {
    "time" : "唐玄宗开元二十五年",
    "events" : ""
  },
  "738" : {
    "time" : "唐玄宗开元二十六年",
    "events" : "李白先后出游于南阳, 嵩山, 陈州(今淮阳), 楚州(今淮安)"
  },
  "739" : {
    "time" : "唐玄宗开元二十七年",
    "events" : "李白先后出游安宜(今扬州宝应县), 姑苏, 后逆长江西上, 经当涂, 至巴陵(今岳阳)结识王昌龄, 后归家安陆"
  },
  "740" : {
    "time" : "唐玄宗开元二十八年",
    "events" : "李白妻许夫人去世, 李白同许家搬迁至任城(今济宁), 后出游兖州"
  },
  "741" : {
    "time" : "唐玄宗开元二十九年",
    "events" : "李白居于任城, 与“竹溪六逸”结识, 期间往来徂徕山,"
  },
  "742" : {
    "time" : "唐玄宗天宝元年",
    "events" : "李白四月与子女游于泰山, 夏至南陵, 后前往越中(今绍兴), 欲游江南, 受贺知章引荐, 遂返南陵, 秋赴长安"
  },
  "743" : {
    "time" : "唐玄宗天宝二年",
    "events" : ""
  },
  "744" : {
    "time" : "唐玄宗天宝三年",
    "events" : "李白三月被玄宗赐金放还, 惆怅不已, 遂登华山, 离长安而去。 后与杜甫相遇于洛阳, 旋往开封, 请北海高天师授其道,决心遁入方外。秋与高适、杜甫共游梁宋区域(今河南省)。冬日北往安陵(今沧州吴桥县)"
  },
  "745" : {
    "time" : "唐玄宗天宝四年",
    "events" : "杜甫于二月来东相访, 二人同游于任城一带。夏与高适、杜甫同谒北海太守李邕于济南。秋与杜甫复会于鲁郡(今曲阜)。冬日在鲁郡(今曲阜)别杜甫, 出游金乡(今济宁金乡县)、单父(今菏泽单县)"
  },
  "746" : {
    "time" : "唐玄宗天宝五年",
    "events" : "李白卧病于任城(今济宁), 秋末病愈至宋城(今商丘)游梁园, 旋到广陵(今扬州)"
  },
  "747" : {
    "time" : "唐玄宗天宝六年",
    "events" : "李白春在广陵(今扬州), 旋至金陵(今南京)遇崔成甫, 随之一同南下。秋到越中(今绍兴)吊贺知章, 后登天台山。冬返金陵(今南京)"
  },
  "748" : {
    "time" : "唐玄宗天宝七年",
    "events" : "李白春在金陵(今南京), 夏至扬州, 秋游霍山(今六安), 冬到庐江(合肥庐江县), 谒见庐江太守吴王李抵"
  },
  "749" : {
    "time" : "唐玄宗天宝八年",
    "events" : "李白途径扬州, 春返金陵(今南京),"
  },
  "750" : {
    "time" : "唐玄宗天宝九年",
    "events" : "李白夏往庐山。秋至浔阳(今九江), 元丹丘自叶县来信相邀, 旋北还，途经谯郡(今亳州)访友人元演。东至任城(今济宁)"
  },
  "751" : {
    "time" : "唐玄宗天宝十年",
    "events" : "李白春在任城(今济宁), 秋滞留在叶县。秋末, 自开封沿河北道北游范阳(今北京), 途经邺郡(今安阳)、邯郸、定州(今保定)"
  },
  "752" : {
    "time" : "唐玄宗天宝十一年",
    "events" : "李白十月到达范阳(今北京)"
  },
  "753" : {
    "time" : "唐玄宗天宝十二年",
    "events" : "李白为避安禄山叛乱, 自范阳(今北京)南下魏郡(今邯郸魏县), 游西河郡(今吕梁汾阳市), 继续沿汾河、黄河南下至长安。后至历阳(今马鞍山和县)。秋又南下游句溪、敬亭山等地"
  },
  "754" : {
    "time" : "唐玄宗天宝十三年",
    "events" : "李白春游金陵, 五月至扬州, 后与王屋山人魏万相遇, 二人同游金陵(今南京), 分别后李白继游溧阳、南陵、秋浦(今池州贵池县)、青阳、陉县等地"
  },
  "755" : {
    "time" : "唐玄宗天宝十四年",
    "events" : "李白继续游宣城一带, 冬返宣城, 旋至金陵(今南京)"
  },
  "756" : {
    "time" : "唐肃宗至德元年",
    "events" : "安禄山发动叛乱, 李白与妻子宗氏南奔避难。春在当涂, 闻洛阳失陷, 乃自当涂返宣城, 避难至潥阳, 夏至杭州。后闻郭子仪、李光弼在河北大胜, 遂返金陵。秋, 闻玄宗奔蜀, 遂沿长江西上, 入庐山隐居。 永王听闻, 数次下达聘书, 李白于是决定下山在九江做其幕僚"
  },
  "757" : {
    "time" : "唐肃宗至德二年",
    "events" : "正月永王兵败丹阳, 李白自丹阳南逃未遂, 被缚入浔阳(今九江)狱中, 被宋若思救出狱后, 跟随其前往武昌(今鄂州), 后避祸前往司空山, 九月, 李白病卧宿松, 以参加永王东巡而被判罪长流夜郎"
  },
  "758" : {
    "time" : "唐肃宗乾元元年",
    "events" : "李白自浔阳(今九江)出发，开始长流夜郎, 途经西塞驿(今黄石境内), 至江夏(今武汉), 登黄鹤楼, 眺望鹦鹉洲。秋至荆州(今江陵), 冬入三峡"
  },
  "759" : {
    "time" : "唐肃宗乾元二年",
    "events" : "流放途中至白帝城时遇赦(今重庆奉节县), 欲返当涂, 其间曾游洞庭湖, 零陵(今永州)等地, 初夏至江夏(今武汉), 留滞到冬"
  },
  "760" : {
    "time" : "唐肃宗上元元年",
    "events" : "秋至浔阳, 再登庐山, 岁末至豫章(今南昌)"
  },
  "761" : {
    "time" : "唐肃宗上元二年",
    "events" : "李白流落金陵一带, 靠人赈济为生, 寄宿于当涂县令李阳冰处"
  },
  "762" : {
    "time" : "唐代宗宝应元年",
    "events" : "早春, 卧病当涂。晚春三月, 作最后的一次旅行, 游宣城、南陵。后卒于当涂"
  }
}